ha_silabs_firmware_client/__init__.py
ha_silabs_firmware_client/client.py
ha_silabs_firmware_client/models.py
ha_silabs_firmware_client/py.typed
ha_silabs_firmware_client-0.2.0.dist-info/LICENSE
ha_silabs_firmware_client-0.2.0.dist-info/METADATA
ha_silabs_firmware_client-0.2.0.dist-info/WHEEL
ha_silabs_firmware_client-0.2.0.dist-info/top_level.txt
ha_silabs_firmware_client-0.2.0.dist-info/RECORD
